README.txt
setup.py
Products/__init__.py
Products.AutoRole.egg-info/PKG-INFO
Products.AutoRole.egg-info/SOURCES.txt
Products.AutoRole.egg-info/dependency_links.txt
Products.AutoRole.egg-info/entry_points.txt
Products.AutoRole.egg-info/namespace_packages.txt
Products.AutoRole.egg-info/not-zip-safe
Products.AutoRole.egg-info/requires.txt
Products.AutoRole.egg-info/top_level.txt
Products/AutoRole/__init__.py
Products/AutoRole/configure.zcml
Products/AutoRole/interfaces.py
Products/AutoRole/setuphandlers.py
Products/AutoRole/version.txt
Products/AutoRole/plugins/AutoRole.py
Products/AutoRole/plugins/__init__.py
Products/AutoRole/plugins/www/autoRoleAdd.zpt
Products/AutoRole/profiles/default/autorole.txt
Products/AutoRole/profiles/default/metadata.xml
Products/AutoRole/tests/__init__.py
Products/AutoRole/tests/testAutoRole.py
Products/AutoRole/tests/testCompiler.py
Products/AutoRole/tests/testEvent.py
docs/HISTORY.txt
docs/INSTALL.txt
docs/LICENSE.LGPL
docs/LICENSE.txt
docs/README-1.x.txt