Metadata-Version: 1.0
Name: Products.AutoRole
Version: 2.1.1
Summary: PAS plugin for adding roles to (anonymous or logged-in) visitors based on their IP address.
Home-page: http://plone.org/products/autorole
Author: Jarn
Author-email: info@jarn.com
License: LGPL
Keywords: autorole pas plugin roles groups
Platform: UNKNOWN
Classifier: Framework :: Plone
Classifier: Framework :: Zope2
Classifier: Programming Language :: Python
Classifier: Topic :: Software Development :: Libraries :: Python Modules
